bfrac/__about__.py
bfrac/__init__.py
bfrac/app_config.py
bfrac/match_info_object.py
bfrac/query_context.py
bfrac/riot_api_caller.py
bfrac/riot_api_helper.py
bfrac-0.0.53.dist-info/METADATA
bfrac-0.0.53.dist-info/WHEEL
bfrac-0.0.53.dist-info/licenses/LICENSE
bfrac-0.0.53.dist-info/RECORD
