Metadata-Version: 2.1
Name: bfrac
Version: 0.0.53
Summary: Beginner Friendly Riot API Caller is a simple wrapper for RiotAPI with rate maintenance built in.
Project-URL: Documentation, https://github.com/deamonpog/bfrac#readme
Project-URL: Issues, https://github.com/deamonpog/bfrac/issues
Project-URL: Source, https://github.com/deamonpog/bfrac
Author-email: deamonpog <pog666@gmail.com>
License-Expression: MIT
License-File: LICENSE
Classifier: Development Status :: 4 - Beta
Classifier: Programming Language :: Python
Classifier: Programming Language :: Python :: 3.7
Classifier: Programming Language :: Python :: 3.8
Classifier: Programming Language :: Python :: 3.9
Classifier: Programming Language :: Python :: 3.10
Classifier: Programming Language :: Python :: 3.11
Classifier: Programming Language :: Python :: Implementation :: CPython
Classifier: Programming Language :: Python :: Implementation :: PyPy
Requires-Python: >=3.7
